vtuna/__init__.py
vtuna/_cli/__init__.py
vtuna/_cli/vtuna.py
vtuna/config/__init__.py
vtuna/config/_errors.py
vtuna/config/_instantiate.py
vtuna/config/_parse.py
vtuna/config/_utils.py
vtuna/config/_validate.py
vtuna-0.1.0.dist-info/LICENSE
vtuna-0.1.0.dist-info/METADATA
vtuna-0.1.0.dist-info/WHEEL
vtuna-0.1.0.dist-info/entry_points.txt
vtuna-0.1.0.dist-info/top_level.txt
vtuna-0.1.0.dist-info/RECORD
