Metadata-Version: 2.1
Name: vtuna
Version: 0.1.0
Summary: A library for tuning adapters for visual generation models
Author: Ray Wang
License: Apache License
Project-URL: GitHub, https://github.com/budui/vtuna
Project-URL: Issues, https://github.com/budui/vtuna/issues
Keywords: pytorch,finetuning,adapting,diffusion
Requires-Python: >=3.8
License-File: LICENSE
Requires-Dist: datasets
Requires-Dist: huggingface-hub
Requires-Dist: safetensors
Requires-Dist: diffusers
Requires-Dist: fire
Requires-Dist: loguru
Requires-Dist: tqdm
Requires-Dist: omegaconf
Provides-Extra: dev
Requires-Dist: tensorboard ; extra == 'dev'
